marker/builders/__init__.py
marker/builders/document.py
marker/builders/layout.py
marker/builders/line.py
marker/builders/ocr.py
marker/builders/structure.py
marker/config/__init__.py
marker/config/crawler.py
marker/config/parser.py
marker/config/printer.py
marker/converters/__init__.py
marker/converters/extraction.py
marker/converters/ocr.py
marker/converters/pdf.py
marker/converters/table.py
marker/extractors/__init__.py
marker/extractors/document.py
marker/extractors/page.py
marker/logger.py
marker/models.py
marker/output.py
marker/processors/__init__.py
marker/processors/blank_page.py
marker/processors/block_relabel.py
marker/processors/blockquote.py
marker/processors/code.py
marker/processors/debug.py
marker/processors/document_toc.py
marker/processors/equation.py
marker/processors/footnote.py
marker/processors/ignoretext.py
marker/processors/line_merge.py
marker/processors/line_numbers.py
marker/processors/list.py
marker/processors/llm/__init__.py
marker/processors/llm/llm_complex.py
marker/processors/llm/llm_equation.py
marker/processors/llm/llm_form.py
marker/processors/llm/llm_handwriting.py
marker/processors/llm/llm_image_description.py
marker/processors/llm/llm_mathblock.py
marker/processors/llm/llm_meta.py
marker/processors/llm/llm_page_correction.py
marker/processors/llm/llm_sectionheader.py
marker/processors/llm/llm_table.py
marker/processors/llm/llm_table_merge.py
marker/processors/order.py
marker/processors/page_header.py
marker/processors/reference.py
marker/processors/sectionheader.py
marker/processors/table.py
marker/processors/text.py
marker/processors/util.py
marker/providers/__init__.py
marker/providers/document.py
marker/providers/epub.py
marker/providers/html.py
marker/providers/image.py
marker/providers/pdf.py
marker/providers/powerpoint.py
marker/providers/registry.py
marker/providers/spreadsheet.py
marker/providers/utils.py
marker/renderers/__init__.py
marker/renderers/chunk.py
marker/renderers/extraction.py
marker/renderers/html.py
marker_pdf-1.10.2.dist-info/METADATA
marker_pdf-1.10.2.dist-info/WHEEL
marker_pdf-1.10.2.dist-info/entry_points.txt
marker_pdf-1.10.2.dist-info/licenses/LICENSE
marker_pdf-1.10.2.dist-info/RECORD
