Metadata-Version: 2.4
Name: marker-pdf
Version: 1.10.2
Summary: Convert documents to markdown with high speed and accuracy.
License: GPL-3.0-or-later
License-File: LICENSE
Keywords: pdf,markdown,ocr,nlp
Author: Vik Paruchuri
Author-email: github@vikas.sh
Requires-Python: >=3.10,<4.0
Classifier: License :: OSI Approved :: GNU General Public License v3 or later (GPLv3+)
Classifier: Programming Language :: Python :: 3
Classifier: Programming Language :: Python :: 3.10
Classifier: Programming Language :: Python :: 3.11
Classifier: Programming Language :: Python :: 3.12
Classifier: Programming Language :: Python :: 3.13
Classifier: Programming Language :: Python :: 3.14
Provides-Extra: full
Requires-Dist: Pillow (>=10.1.0,<11.0.0)
Requires-Dist: anthropic (>=0.46.0,<0.47.0)
Requires-Dist: click (>=8.2.0,<9.0.0)
Requires-Dist: ebooklib (>=0.18,<0.19) ; extra == "full"
Requires-Dist: filetype (>=1.2.0,<2.0.0)
Requires-Dist: ftfy (>=6.1.1,<7.0.0)
Requires-Dist: google-genai (>=1.0.0,<2.0.0)
Requires-Dist: mammoth (>=1.9.0,<2.0.0) ; extra == "full"
Requires-Dist: markdown2 (>=2.5.2,<3.0.0)
Requires-Dist: markdownify (>=1.1.0,<2.0.0)
Requires-Dist: openai (>=1.65.2,<2.0.0)
Requires-Dist: openpyxl (>=3.1.5,<4.0.0) ; extra == "full"
Requires-Dist: pdftext (>=0.6.3,<0.7.0)
Requires-Dist: pre-commit (>=4.2.0,<5.0.0)
Requires-Dist: pydantic (>=2.4.2,<3.0.0)
Requires-Dist: pydantic-settings (>=2.0.3,<3.0.0)
Requires-Dist: python-dotenv (>=1.0.0,<2.0.0)
Requires-Dist: python-pptx (>=1.0.2,<2.0.0) ; extra == "full"
Requires-Dist: rapidfuzz (>=3.8.1,<4.0.0)
Requires-Dist: regex (>=2024.4.28,<2025.0.0)
Requires-Dist: scikit-learn (>=1.6.1,<2.0.0)
Requires-Dist: surya-ocr (>=0.17.1,<0.18.0)
Requires-Dist: torch (>=2.7.0,<3.0.0)
Requires-Dist: tqdm (>=4.66.1,<5.0.0)
Requires-Dist: transformers (>=4.45.2,<5.0.0)
Requires-Dist: weasyprint (>=63.1,<64.0) ; extra == "full"
Project-URL: Repository, https://github.com/VikParuchuri/marker
